pywiggle/__init__.py
pywiggle/_wiggle.cpython-313-i386-linux-musl.so
pywiggle/core.py
pywiggle/utils.py
pywiggle/data/test_camb_cl.npz
pywiggle/tests/__init__.py
pywiggle/tests/test_bench.py
pywiggle/tests/test_utils.py
pywiggle/tests/test_wiggle.py
pywiggle/tests/test_wignerd.py
pywiggle.libs/libgcc_s-887de51c.so.1
pywiggle.libs/libgomp-24921df4.so.1.0.0
pywiggle.libs/libstdc++-d6415257.so.6.0.33
pywiggle-0.1.18.dist-info/METADATA
pywiggle-0.1.18.dist-info/WHEEL
pywiggle-0.1.18.dist-info/RECORD
