Metadata-Version: 2.1
Name: pywiggle
Version: 0.1.18
Summary: Fast angular power spectrum estimator
Author-Email: Mathew Madhavacheril <mathewsyriac@gmail.com>
License: MIT
Project-URL: Homepage, https://github.com/msyriac/wiggle
Requires-Python: >=3.10
Requires-Dist: numpy
Requires-Dist: pybind11>=2.11
Requires-Dist: healpy
Requires-Dist: fastgl>=0.1.11
Requires-Dist: scipy>=1.0
Requires-Dist: threadpoolctl
Provides-Extra: test
Requires-Dist: pytest-cov>=2.6; extra == "test"
Requires-Dist: coveralls>=1.5; extra == "test"
Requires-Dist: pytest>=4.6; extra == "test"
Requires-Dist: ducc0; extra == "test"
Requires-Dist: pixell; extra == "test"
Requires-Dist: matplotlib; extra == "test"
